json2rdf/__init__.py
json2rdf/cli.py
json2rdf/json2rdf.py
json2rdf-79.dist-info/METADATA
json2rdf-79.dist-info/WHEEL
json2rdf-79.dist-info/entry_points.txt
json2rdf-79.dist-info/RECORD
