Metadata-Version: 2.4
Name: json2rdf
Version: 79
Summary: Translate JSON to RDF
Project-URL: Repository, https://github.com/pnnl/json2rdf.git
Author-email: Majid alDosari <majid.aldosari@pnnl.gov>, Majid alDosari <majidaldosari-github@yahoo.com>
Requires-Python: >=3.11
Requires-Dist: boltons
Requires-Dist: numpy
Provides-Extra: cli
Requires-Dist: fire; extra == 'cli'
